{
  "id": "hyeonri_1951",
  "name": "현리 전투",
  "name_en": "Battle of Hyeonri",
  "era": "korean_war",
  "year": 1951,
  "year_decimal": 1951.39,
  "date_display": "1951년 5월 16-22일",
  "coords": [
    38.085,
    128.305
  ],
  "sides": [
    {
      "name": "중공군 3개 군",
      "commander": "왕건안 · 등화",
      "troops": 70000,
      "casualties": 8000,
      "color": "red",
      "victor": true,
      "symbol": "infantry"
    },
    {
      "name": "국군 3군단 (3·9사단)",
      "commander": "유재흥",
      "troops": 25000,
      "casualties": 19000,
      "color": "blue",
      "victor": false,
      "symbol": "infantry"
    }
  ],
  "tactics": [
    {
      "ko": "지휘 공백 (실패)",
      "en": "Command Vacuum (Failure)",
      "desc": "군단장 헬기 후퇴, 사단장 무전 두절 — 통제 상실의 전형"
    },
    {
      "ko": "돌파 후 포위",
      "en": "Penetration & Envelopment",
      "desc": "중공군이 오마치 고개 선점으로 후방 차단"
    },
    {
      "ko": "심리 와해",
      "en": "Psychological Collapse",
      "desc": "포위 인지 후 부대 통제 상실, 무질서 후퇴 → 7000명 실종"
    }
  ],
  "significance": "<strong>한국군 최악의 패배이자 가장 값비싼 교훈.</strong> 밴 플리트는 이후 한국군 군단을 일시 해체. <strong>\"지휘관이 부대를 떠나는 순간 부대는 무너진다\"</strong>는 명제. 현대 한국군 지휘 교리의 기반 사례.",
  "description": "5월 공세에서 중공군이 좁은 오마치 고개를 야간 침투로 선점. 군단장 유재흥은 헬기로 후방 이동, 사단들은 통제 상실. 무질서 후퇴로 중장비 거의 전량 유기, 실종 7000명. 이 한 차례 패배로 한국군은 1년간 군단급 작전권 박탈. 한국군 지휘참모대학 필수 교범 사례.",
  "influenced_by": [],
  "influences": [],
  "has_simulation": false,
  "sources": [
    {
      "type": "book",
      "citation": "국방부 군사편찬연구소. 6·25전쟁사 9권: 38도선 일대 격전."
    }
  ],
  "wikidata_id": null,
  "wikipedia": {
    "ko": "https://ko.wikipedia.org/wiki/현리_전투",
    "en": null
  },
  "contributors": [],
  "last_reviewed": null,
  "review_status": "community"
}
